goxlr/__init__.py
goxlr/_version.py
goxlr/error.py
goxlr/socket.py
goxlr/commands/__init__.py
goxlr/commands/daemon.py
goxlr/commands/goxlr.py
goxlr/commands/status.py
goxlr/types/__init__.py
goxlr/types/enums.py
goxlr/types/models.py
goxlr-1.4.8.dist-info/licenses/LICENSE-3RD-PARTY.txt
goxlr-1.4.8.dist-info/licenses/LICENSE.txt
goxlr-1.4.8.dist-info/METADATA
goxlr-1.4.8.dist-info/WHEEL
goxlr-1.4.8.dist-info/top_level.txt
goxlr-1.4.8.dist-info/RECORD
