Metadata-Version: 2.4
Name: goxlr
Version: 1.4.8
Summary: A Python wrapper for the GoXLR Utility API.
Home-page: https://github.com/samcarsonx/goxlr-py
Author: Sam Carson
Author-email: sam@samcarson.co.uk
License: MIT
Requires-Python: >=3.10
License-File: LICENSE-3RD-PARTY.txt
License-File: LICENSE.txt
Requires-Dist: asyncio
Requires-Dist: websockets==13.1
Dynamic: author
Dynamic: author-email
Dynamic: description
Dynamic: description-content-type
Dynamic: home-page
Dynamic: license
Dynamic: license-file
Dynamic: requires-dist
Dynamic: requires-python
Dynamic: summary
